{"active":false,"project_no":"50312","title":" GREENLEAF GARDENS","image":"fy11-84_1.jpg","agency":"DEPT. OF HOUSING AND COMM. DEVELOPMENT (DB0)","implementing_agency":"DEPT. OF HOUSING AND COMM. DEVELOPMENT (DB0)","ward":"6","location":"201 M STREET SW","status":"Predesign","description":"In a joint venture arrangement with one or more private developers, the current 489 units at the Greenleaf Gardens development will be replaced with mixed income units both on and off site in the immediate surrounding neighborhood. The neighborhood in which this property is located has great potential for commercial, office, or retail development and thus greater opportunity for one-for-one replacement.","justification":"One for one replacement of 489 public housing units in a mixed income setting in order to assure retention of these affordable units for long term. This project fits into the Mayor’s, DHCD’s and the DC Housing Authority's priorities and plans for retaining affordable housing. This project supports the Mayor’s priorities and plans for maintaining the level of affordable housing stock in the District.","progress_assessment":"DCHA is preparing the development scope of work for this project. The project is currently on schedule.","related_projects":"None.","milestones":{"environmental_approvals":{"projected":"10/30/09"},"design_start":{"projected":"11/30/09"},"design_complete":{"projected":"03/30/11","actual":"03/30/11"},"construction_start":{"projected":"06/30/12"},"construction_complete":{"projected":"09/30/16"},"closeout":{"projected":"09/30/17"}},"useful_life":30,"facility":"GREENLEAF GARDENS","lat":38.87672072,"lon":-77.01426782,"first_year":2010,"last_year":2011,"cip_history":{"FY2010":{"plan":{"FY2010":0,"FY2011":1500,"FY2012":0,"FY2013":0,"FY2014":0,"FY2015":0},"est_cost":null},"FY2011":{"plan":{"FY2011":500,"FY2012":0,"FY2013":0,"FY2014":0,"FY2015":0,"FY2016":0},"est_cost":null}},"cumulative_funding":{"funding_by_phase":{"(01) Design":{"FY2010":{"allotted":0,"spent":0,"proposed":0},"FY2011":{"allotted":0,"spent":0,"proposed":500}}},"funding_by_source":{"GO Bonds - New (0300)":{"FY2010":{"allotted":0,"spent":0,"proposed":0},"FY2011":{"allotted":0,"spent":0,"proposed":500}}},"total_funding":{"FY2010":{"allotted":0,"spent":0,"proposed":0},"FY2011":{"allotted":0,"spent":0,"proposed":500}}},"est_cost":500000}